arraylias/VERSION.txt
arraylias/__init__.py
arraylias/alias.py
arraylias/aliased.py
arraylias/exceptions.py
arraylias/version.py
arraylias/default_alias/__init__.py
arraylias/default_alias/numpy_alias.py
arraylias/default_alias/register_jax.py
arraylias/default_alias/register_numpy.py
arraylias/default_alias/register_tensorflow.py
arraylias/default_alias/scipy_alias.py
arraylias-0.1.1.dist-info/LICENSE.txt
arraylias-0.1.1.dist-info/METADATA
arraylias-0.1.1.dist-info/WHEEL
arraylias-0.1.1.dist-info/top_level.txt
arraylias-0.1.1.dist-info/RECORD
