Metadata-Version: 2.1
Name: arraylias
Version: 0.1.1
Summary: A Python package for aliased function dispatching to multiple array libraries
Home-page: https://github.com/Qiskit/arraylias
Author: Christopher J. Wood
Author-email: cjwood@cjwood.com
License: Apache 2.0
Project-URL: Bug Tracker, https://github.com/Qiskit/arraylias/issues
Project-URL: Documentation, https://qiskit-extensions.github.io/arraylias/
Project-URL: Source Code, https://github.com/Qiskit/arraylias
Keywords: array dispatcher qiskit numpy jax tensorflow
Platform: UNKNOWN
Classifier: Environment :: Console
Classifier: License :: OSI Approved :: Apache Software License
Classifier: Intended Audience :: Developers
Classifier: Intended Audience :: Science/Research
Classifier: Operating System :: Microsoft :: Windows
Classifier: Operating System :: MacOS
Classifier: Operating System :: POSIX :: Linux
Classifier: Programming Language :: Python :: 3 :: Only
Classifier: Programming Language :: Python :: 3.9
Classifier: Programming Language :: Python :: 3.10
Classifier: Programming Language :: Python :: 3.11
Classifier: Programming Language :: Python :: 3.12
Classifier: Topic :: Scientific/Engineering
Requires-Python: >=3.9
License-File: LICENSE.txt
